{"identifier":{"url":"doc:\/\/org.swift.tspl\/documentation\/The-Swift-Programming-Language\/AutomaticReferenceCounting","interfaceLanguage":"swift"},"metadata":{"title":"Automatic Reference Counting"},"abstract":[{"type":"text","text":"Model the lifetime of objects and their relationships."}],"primaryContentSections":[{"kind":"content","content":[{"type":"paragraph","inlineContent":[{"text":"Swift uses ","type":"text"},{"inlineContent":[{"type":"text","text":"Automatic Reference Counting"}],"type":"emphasis"},{"type":"text","text":" (ARC)"},{"type":"text","text":" "},{"type":"text","text":"to track and manage your app’s memory usage."},{"type":"text","text":" "},{"text":"In most cases, this means that memory management “just works” in Swift,","type":"text"},{"type":"text","text":" "},{"type":"text","text":"and you don’t need to think about memory management yourself."},{"type":"text","text":" "},{"type":"text","text":"ARC automatically frees up the memory used by class instances"},{"type":"text","text":" "},{"type":"text","text":"when those instances are no longer needed."}]},{"type":"paragraph","inlineContent":[{"text":"However, in a few cases ARC requires more information","type":"text"},{"type":"text","text":" "},{"type":"text","text":"about the relationships between parts of your code"},{"type":"text","text":" "},{"text":"in order to manage memory for you.","type":"text"},{"type":"text","text":" "},{"type":"text","text":"This chapter describes those situations"},{"type":"text","text":" "},{"type":"text","text":"and shows how you enable ARC to manage all of your app’s memory."},{"text":" ","type":"text"},{"type":"text","text":"Using ARC in Swift is very similar to the approach described in"},{"type":"text","text":" "},{"isActive":true,"type":"reference","identifier":"https:\/\/developer.apple.com\/library\/content\/releasenotes\/ObjectiveC\/RN-TransitioningToARC\/Introduction\/Introduction.html"},{"text":" ","type":"text"},{"text":"for using ARC with Objective-C.","type":"text"}]},{"type":"paragraph","inlineContent":[{"type":"text","text":"Reference counting applies only to instances of classes."},{"type":"text","text":" "},{"type":"text","text":"Structures and enumerations are value types, not reference types,"},{"type":"text","text":" "},{"type":"text","text":"and aren’t stored and passed by reference."}]},{"type":"heading","text":"How ARC Works","anchor":"How-ARC-Works","level":2},{"inlineContent":[{"type":"text","text":"Every time you create a new instance of a class,"},{"type":"text","text":" "},{"type":"text","text":"ARC allocates a chunk of memory to store information about that instance."},{"type":"text","text":" "},{"type":"text","text":"This memory holds information about the type of the instance,"},{"type":"text","text":" "},{"text":"together with the values of any stored properties associated with that instance.","type":"text"}],"type":"paragraph"},{"type":"paragraph","inlineContent":[{"type":"text","text":"Additionally, when an instance is no longer needed,"},{"text":" ","type":"text"},{"text":"ARC frees up the memory used by that instance","type":"text"},{"text":" ","type":"text"},{"type":"text","text":"so that the memory can be used for other purposes instead."},{"text":" ","type":"text"},{"text":"This ensures that class instances don’t take up space in memory","type":"text"},{"type":"text","text":" "},{"type":"text","text":"when they’re no longer needed."}]},{"inlineContent":[{"type":"text","text":"However, if ARC were to deallocate an instance that was still in use,"},{"text":" ","type":"text"},{"type":"text","text":"it would no longer be possible to access that instance’s properties,"},{"type":"text","text":" "},{"text":"or call that instance’s methods.","type":"text"},{"type":"text","text":" "},{"type":"text","text":"Indeed, if you tried to access the instance, your app would most likely crash."}],"type":"paragraph"},{"type":"paragraph","inlineContent":[{"type":"text","text":"To make sure that instances don’t disappear while they’re still needed,"},{"type":"text","text":" "},{"type":"text","text":"ARC tracks how many properties, constants, and variables"},{"type":"text","text":" "},{"type":"text","text":"are currently referring to each class instance."},{"type":"text","text":" "},{"type":"text","text":"ARC will not deallocate an instance"},{"text":" ","type":"text"},{"type":"text","text":"as long as at least one active reference to that instance still exists."}]},{"inlineContent":[{"type":"text","text":"To make this possible,"},{"type":"text","text":" "},{"type":"text","text":"whenever you assign a class instance to a property, constant, or variable,"},{"type":"text","text":" "},{"text":"that property, constant, or variable makes a ","type":"text"},{"type":"emphasis","inlineContent":[{"type":"text","text":"strong reference"}]},{"text":" to the instance.","type":"text"},{"type":"text","text":" "},{"type":"text","text":"The reference is called a “strong” reference because"},{"type":"text","text":" "},{"text":"it keeps a firm hold on that instance,","type":"text"},{"text":" ","type":"text"},{"text":"and doesn’t allow it to be deallocated for as long as that strong reference remains.","type":"text"}],"type":"paragraph"},{"type":"heading","level":2,"anchor":"ARC-in-Action","text":"ARC in Action"},{"type":"paragraph","inlineContent":[{"type":"text","text":"Here’s an example of how Automatic Reference Counting works."},{"text":" ","type":"text"},{"type":"text","text":"This example starts with a simple class called "},{"type":"codeVoice","code":"Person"},{"type":"text","text":","},{"text":" ","type":"text"},{"text":"which defines a stored constant property called ","type":"text"},{"code":"name","type":"codeVoice"},{"text":":","type":"text"}]},{"type":"codeListing","code":["class Person {","    let name: String","    init(name: String) {","        self.name = name","        print(\"\\(name) is being initialized\")","    }","    deinit {","        print(\"\\(name) is being deinitialized\")","    }","}"],"syntax":"swift"},{"type":"paragraph","inlineContent":[{"text":"The ","type":"text"},{"type":"codeVoice","code":"Person"},{"type":"text","text":" class has an initializer that sets the instance’s "},{"code":"name","type":"codeVoice"},{"text":" property","type":"text"},{"type":"text","text":" "},{"text":"and prints a message to indicate that initialization is underway.","type":"text"},{"type":"text","text":" "},{"type":"text","text":"The "},{"type":"codeVoice","code":"Person"},{"type":"text","text":" class also has a deinitializer"},{"type":"text","text":" "},{"text":"that prints a message when an instance of the class is deallocated.","type":"text"}]},{"type":"paragraph","inlineContent":[{"text":"The next code snippet defines three variables of type ","type":"text"},{"code":"Person?","type":"codeVoice"},{"type":"text","text":","},{"type":"text","text":" "},{"type":"text","text":"which are used to set up multiple references to a new "},{"type":"codeVoice","code":"Person"},{"type":"text","text":" instance"},{"text":" ","type":"text"},{"text":"in subsequent code snippets.","type":"text"},{"text":" ","type":"text"},{"type":"text","text":"Because these variables are of an optional type ("},{"code":"Person?","type":"codeVoice"},{"type":"text","text":", not "},{"type":"codeVoice","code":"Person"},{"text":"),","type":"text"},{"type":"text","text":" "},{"type":"text","text":"they’re automatically initialized with a value of "},{"code":"nil","type":"codeVoice"},{"type":"text","text":","},{"text":" ","type":"text"},{"type":"text","text":"and don’t currently reference a "},{"code":"Person","type":"codeVoice"},{"type":"text","text":" instance."}]},{"type":"codeListing","syntax":"swift","code":["var reference1: Person?","var reference2: Person?","var reference3: Person?"]},{"type":"paragraph","inlineContent":[{"type":"text","text":"You can now create a new "},{"type":"codeVoice","code":"Person"},{"text":" instance","type":"text"},{"type":"text","text":" "},{"text":"and assign it to one of these three variables:","type":"text"}]},{"type":"codeListing","code":["reference1 = Person(name: \"John Appleseed\")","\/\/ Prints \"John Appleseed is being initialized\""],"syntax":"swift"},{"type":"paragraph","inlineContent":[{"type":"text","text":"Note that the message "},{"code":"\"John Appleseed is being initialized\"","type":"codeVoice"},{"text":" is printed","type":"text"},{"text":" ","type":"text"},{"type":"text","text":"at the point that you call the "},{"type":"codeVoice","code":"Person"},{"text":" class’s initializer.","type":"text"},{"type":"text","text":" "},{"type":"text","text":"This confirms that initialization has taken place."}]},{"type":"paragraph","inlineContent":[{"type":"text","text":"Because the new "},{"type":"codeVoice","code":"Person"},{"type":"text","text":" instance has been assigned to the "},{"type":"codeVoice","code":"reference1"},{"type":"text","text":" variable,"},{"text":" ","type":"text"},{"text":"there’s now a strong reference from ","type":"text"},{"type":"codeVoice","code":"reference1"},{"text":" to the new ","type":"text"},{"type":"codeVoice","code":"Person"},{"text":" instance.","type":"text"},{"text":" ","type":"text"},{"text":"Because there’s at least one strong reference,","type":"text"},{"type":"text","text":" "},{"type":"text","text":"ARC makes sure that this "},{"type":"codeVoice","code":"Person"},{"text":" is kept in memory and isn’t deallocated.","type":"text"}]},{"inlineContent":[{"type":"text","text":"If you assign the same "},{"code":"Person","type":"codeVoice"},{"type":"text","text":" instance to two more variables,"},{"type":"text","text":" "},{"type":"text","text":"two more strong references to that instance are established:"}],"type":"paragraph"},{"syntax":"swift","code":["reference2 = reference1","reference3 = reference1"],"type":"codeListing"},{"inlineContent":[{"text":"There are now ","type":"text"},{"inlineContent":[{"type":"text","text":"three"}],"type":"emphasis"},{"text":" strong references to this single ","type":"text"},{"type":"codeVoice","code":"Person"},{"text":" instance.","type":"text"}],"type":"paragraph"},{"type":"paragraph","inlineContent":[{"text":"If you break two of these strong references (including the original reference)","type":"text"},{"type":"text","text":" "},{"text":"by assigning ","type":"text"},{"type":"codeVoice","code":"nil"},{"text":" to two of the variables,","type":"text"},{"type":"text","text":" "},{"type":"text","text":"a single strong reference remains,"},{"type":"text","text":" "},{"text":"and the ","type":"text"},{"code":"Person","type":"codeVoice"},{"type":"text","text":" instance isn’t deallocated:"}]},{"code":["reference1 = nil","reference2 = nil"],"syntax":"swift","type":"codeListing"},{"inlineContent":[{"text":"ARC doesn’t deallocate the ","type":"text"},{"code":"Person","type":"codeVoice"},{"text":" instance until","type":"text"},{"type":"text","text":" "},{"type":"text","text":"the third and final strong reference is broken,"},{"text":" ","type":"text"},{"text":"at which point it’s clear that you are no longer using the ","type":"text"},{"code":"Person","type":"codeVoice"},{"type":"text","text":" instance:"}],"type":"paragraph"},{"syntax":"swift","type":"codeListing","code":["reference3 = nil","\/\/ Prints \"John Appleseed is being deinitialized\""]},{"type":"heading","text":"Strong Reference Cycles Between Class Instances","level":2,"anchor":"Strong-Reference-Cycles-Between-Class-Instances"},{"inlineContent":[{"type":"text","text":"In the examples above,"},{"type":"text","text":" "},{"type":"text","text":"ARC is able to track the number of references to the new "},{"type":"codeVoice","code":"Person"},{"text":" instance you create","type":"text"},{"type":"text","text":" "},{"type":"text","text":"and to deallocate that "},{"code":"Person","type":"codeVoice"},{"text":" instance when it’s no longer needed.","type":"text"}],"type":"paragraph"},{"type":"paragraph","inlineContent":[{"type":"text","text":"However, it’s possible to write code in which an instance of a class"},{"type":"text","text":" "},{"type":"emphasis","inlineContent":[{"type":"text","text":"never"}]},{"text":" gets to a point where it has zero strong references.","type":"text"},{"text":" ","type":"text"},{"type":"text","text":"This can happen if two class instances hold a strong reference to each other,"},{"type":"text","text":" "},{"text":"such that each instance keeps the other alive.","type":"text"},{"type":"text","text":" "},{"type":"text","text":"This is known as a "},{"inlineContent":[{"type":"text","text":"strong reference cycle"}],"type":"emphasis"},{"text":".","type":"text"}]},{"inlineContent":[{"type":"text","text":"You resolve strong reference cycles"},{"type":"text","text":" "},{"text":"by defining some of the relationships between classes","type":"text"},{"type":"text","text":" "},{"text":"as weak or unowned references instead of as strong references.","type":"text"},{"text":" ","type":"text"},{"type":"text","text":"This process is described in"},{"text":" ","type":"text"},{"isActive":true,"type":"reference","identifier":"doc:\/\/org.swift.tspl\/documentation\/The-Swift-Programming-Language\/AutomaticReferenceCounting#Resolving-Strong-Reference-Cycles-Between-Class-Instances"},{"type":"text","text":"."},{"type":"text","text":" "},{"text":"However, before you learn how to resolve a strong reference cycle,","type":"text"},{"text":" ","type":"text"},{"text":"it’s useful to understand how such a cycle is caused.","type":"text"}],"type":"paragraph"},{"inlineContent":[{"type":"text","text":"Here’s an example of how a strong reference cycle can be created by accident."},{"text":" ","type":"text"},{"type":"text","text":"This example defines two classes called "},{"type":"codeVoice","code":"Person"},{"text":" and ","type":"text"},{"type":"codeVoice","code":"Apartment"},{"text":",","type":"text"},{"type":"text","text":" "},{"type":"text","text":"which model a block of apartments and its residents:"}],"type":"paragraph"},{"type":"codeListing","syntax":"swift","code":["class Person {","    let name: String","    init(name: String) { self.name = name }","    var apartment: Apartment?","    deinit { print(\"\\(name) is being deinitialized\") }","}","","class Apartment {","    let unit: String","    init(unit: String) { self.unit = unit }","    var tenant: Person?","    deinit { print(\"Apartment \\(unit) is being deinitialized\") }","}"]},{"type":"paragraph","inlineContent":[{"text":"Every ","type":"text"},{"type":"codeVoice","code":"Person"},{"text":" instance has a ","type":"text"},{"type":"codeVoice","code":"name"},{"text":" property of type ","type":"text"},{"type":"codeVoice","code":"String"},{"text":" ","type":"text"},{"text":"and an optional ","type":"text"},{"type":"codeVoice","code":"apartment"},{"text":" property that’s initially ","type":"text"},{"code":"nil","type":"codeVoice"},{"text":".","type":"text"},{"type":"text","text":" "},{"text":"The ","type":"text"},{"type":"codeVoice","code":"apartment"},{"text":" property is optional, because a person may not always have an apartment.","type":"text"}]},{"type":"paragraph","inlineContent":[{"type":"text","text":"Similarly, every "},{"type":"codeVoice","code":"Apartment"},{"text":" instance has a ","type":"text"},{"code":"unit","type":"codeVoice"},{"type":"text","text":" property of type "},{"code":"String","type":"codeVoice"},{"type":"text","text":" "},{"type":"text","text":"and has an optional "},{"type":"codeVoice","code":"tenant"},{"text":" property that’s initially ","type":"text"},{"type":"codeVoice","code":"nil"},{"type":"text","text":"."},{"type":"text","text":" "},{"type":"text","text":"The tenant property is optional because an apartment may not always have a tenant."}]},{"inlineContent":[{"text":"Both of these classes also define a deinitializer,","type":"text"},{"text":" ","type":"text"},{"type":"text","text":"which prints the fact that an instance of that class is being deinitialized."},{"text":" ","type":"text"},{"text":"This enables you to see whether","type":"text"},{"type":"text","text":" "},{"text":"instances of ","type":"text"},{"type":"codeVoice","code":"Person"},{"type":"text","text":" and "},{"type":"codeVoice","code":"Apartment"},{"text":" are being deallocated as expected.","type":"text"}],"type":"paragraph"},{"type":"paragraph","inlineContent":[{"text":"This next code snippet defines two variables of optional type","type":"text"},{"text":" ","type":"text"},{"type":"text","text":"called "},{"type":"codeVoice","code":"john"},{"type":"text","text":" and "},{"type":"codeVoice","code":"unit4A"},{"text":",","type":"text"},{"type":"text","text":" "},{"text":"which will be set to a specific ","type":"text"},{"type":"codeVoice","code":"Apartment"},{"type":"text","text":" and "},{"code":"Person","type":"codeVoice"},{"text":" instance below.","type":"text"},{"type":"text","text":" "},{"text":"Both of these variables have an initial value of ","type":"text"},{"type":"codeVoice","code":"nil"},{"type":"text","text":", by virtue of being optional:"}]},{"syntax":"swift","code":["var john: Person?","var unit4A: Apartment?"],"type":"codeListing"},{"inlineContent":[{"text":"You can now create a specific ","type":"text"},{"type":"codeVoice","code":"Person"},{"type":"text","text":" instance and "},{"code":"Apartment","type":"codeVoice"},{"text":" instance","type":"text"},{"type":"text","text":" "},{"type":"text","text":"and assign these new instances to the "},{"code":"john","type":"codeVoice"},{"text":" and ","type":"text"},{"type":"codeVoice","code":"unit4A"},{"type":"text","text":" variables:"}],"type":"paragraph"},{"code":["john = Person(name: \"John Appleseed\")","unit4A = Apartment(unit: \"4A\")"],"type":"codeListing","syntax":"swift"},{"inlineContent":[{"type":"text","text":"Here’s how the strong references look after creating and assigning these two instances."},{"type":"text","text":" "},{"type":"text","text":"The "},{"type":"codeVoice","code":"john"},{"type":"text","text":" variable now has a strong reference to the new "},{"type":"codeVoice","code":"Person"},{"type":"text","text":" instance,"},{"type":"text","text":" "},{"type":"text","text":"and the "},{"type":"codeVoice","code":"unit4A"},{"text":" variable has a strong reference to the new ","type":"text"},{"type":"codeVoice","code":"Apartment"},{"text":" instance:","type":"text"}],"type":"paragraph"},{"type":"paragraph","inlineContent":[{"identifier":"referenceCycle01","type":"image"}]},{"inlineContent":[{"text":"You can now link the two instances together","type":"text"},{"text":" ","type":"text"},{"text":"so that the person has an apartment, and the apartment has a tenant.","type":"text"},{"type":"text","text":" "},{"type":"text","text":"Note that an exclamation point ("},{"code":"!","type":"codeVoice"},{"text":") is used to unwrap and access","type":"text"},{"text":" ","type":"text"},{"text":"the instances stored inside the ","type":"text"},{"type":"codeVoice","code":"john"},{"type":"text","text":" and "},{"code":"unit4A","type":"codeVoice"},{"type":"text","text":" optional variables,"},{"type":"text","text":" "},{"text":"so that the properties of those instances can be set:","type":"text"}],"type":"paragraph"},{"code":["john!.apartment = unit4A","unit4A!.tenant = john"],"type":"codeListing","syntax":"swift"},{"inlineContent":[{"text":"Here’s how the strong references look after you link the two instances together:","type":"text"}],"type":"paragraph"},{"type":"paragraph","inlineContent":[{"type":"image","identifier":"referenceCycle02"}]},{"type":"paragraph","inlineContent":[{"type":"text","text":"Unfortunately, linking these two instances creates"},{"type":"text","text":" "},{"text":"a strong reference cycle between them.","type":"text"},{"type":"text","text":" "},{"type":"text","text":"The "},{"code":"Person","type":"codeVoice"},{"type":"text","text":" instance now has a strong reference to the "},{"code":"Apartment","type":"codeVoice"},{"text":" instance,","type":"text"},{"type":"text","text":" "},{"type":"text","text":"and the "},{"type":"codeVoice","code":"Apartment"},{"type":"text","text":" instance has a strong reference to the "},{"type":"codeVoice","code":"Person"},{"type":"text","text":" instance."},{"type":"text","text":" "},{"type":"text","text":"Therefore, when you break the strong references held by"},{"text":" ","type":"text"},{"type":"text","text":"the "},{"code":"john","type":"codeVoice"},{"type":"text","text":" and "},{"type":"codeVoice","code":"unit4A"},{"text":" variables,","type":"text"},{"type":"text","text":" "},{"text":"the reference counts don’t drop to zero,","type":"text"},{"type":"text","text":" "},{"type":"text","text":"and the instances aren’t deallocated by ARC:"}]},{"code":["john = nil","unit4A = nil"],"syntax":"swift","type":"codeListing"},{"type":"paragraph","inlineContent":[{"text":"Note that neither deinitializer was called","type":"text"},{"text":" ","type":"text"},{"text":"when you set these two variables to ","type":"text"},{"type":"codeVoice","code":"nil"},{"type":"text","text":"."},{"text":" ","type":"text"},{"text":"The strong reference cycle prevents the ","type":"text"},{"code":"Person","type":"codeVoice"},{"type":"text","text":" and "},{"code":"Apartment","type":"codeVoice"},{"type":"text","text":" instances"},{"type":"text","text":" "},{"text":"from ever being deallocated, causing a memory leak in your app.","type":"text"}]},{"type":"paragraph","inlineContent":[{"type":"text","text":"Here’s how the strong references look after you set"},{"text":" ","type":"text"},{"type":"text","text":"the "},{"code":"john","type":"codeVoice"},{"type":"text","text":" and "},{"code":"unit4A","type":"codeVoice"},{"type":"text","text":" variables to "},{"type":"codeVoice","code":"nil"},{"text":":","type":"text"}]},{"type":"paragraph","inlineContent":[{"identifier":"referenceCycle03","type":"image"}]},{"inlineContent":[{"type":"text","text":"The strong references between the "},{"type":"codeVoice","code":"Person"},{"type":"text","text":" instance"},{"text":" ","type":"text"},{"type":"text","text":"and the "},{"code":"Apartment","type":"codeVoice"},{"text":" instance remain and can’t be broken.","type":"text"}],"type":"paragraph"},{"level":2,"anchor":"Resolving-Strong-Reference-Cycles-Between-Class-Instances","text":"Resolving Strong Reference Cycles Between Class Instances","type":"heading"},{"type":"paragraph","inlineContent":[{"type":"text","text":"Swift provides two ways to resolve strong reference cycles"},{"type":"text","text":" "},{"type":"text","text":"when you work with properties of class type:"},{"text":" ","type":"text"},{"type":"text","text":"weak references and unowned references."}]},{"type":"paragraph","inlineContent":[{"type":"text","text":"Weak and unowned references enable one instance in a reference cycle"},{"text":" ","type":"text"},{"text":"to refer to the other instance ","type":"text"},{"inlineContent":[{"type":"text","text":"without"}],"type":"emphasis"},{"text":" keeping a strong hold on it.","type":"text"},{"text":" ","type":"text"},{"text":"The instances can then refer to each other without creating a strong reference cycle.","type":"text"}]},{"type":"paragraph","inlineContent":[{"type":"text","text":"Use a weak reference when the other instance has a shorter lifetime —"},{"text":" ","type":"text"},{"type":"text","text":"that is, when the other instance can be deallocated first."},{"type":"text","text":" "},{"type":"text","text":"In the "},{"type":"codeVoice","code":"Apartment"},{"text":" example above,","type":"text"},{"text":" ","type":"text"},{"type":"text","text":"it’s appropriate for an apartment to be able to have"},{"text":" ","type":"text"},{"text":"no tenant at some point in its lifetime,","type":"text"},{"type":"text","text":" "},{"type":"text","text":"and so a weak reference is an appropriate way to break the reference cycle in this case."},{"type":"text","text":" "},{"text":"In contrast, use an unowned reference when the other instance","type":"text"},{"text":" ","type":"text"},{"text":"has the same lifetime or a longer lifetime.","type":"text"}]},{"type":"heading","level":3,"anchor":"Weak-References","text":"Weak References"},{"inlineContent":[{"type":"text","text":"A "},{"type":"emphasis","inlineContent":[{"type":"text","text":"weak reference"}]},{"text":" is a reference that doesn’t keep a strong hold","type":"text"},{"text":" ","type":"text"},{"text":"on the instance it refers to,","type":"text"},{"type":"text","text":" "},{"text":"and so doesn’t stop ARC from disposing of the referenced instance.","type":"text"},{"type":"text","text":" "},{"type":"text","text":"This behavior prevents the reference from becoming part of a strong reference cycle."},{"text":" ","type":"text"},{"type":"text","text":"You indicate a weak reference by placing the "},{"type":"codeVoice","code":"weak"},{"type":"text","text":" keyword"},{"text":" ","type":"text"},{"type":"text","text":"before a property or variable declaration."}],"type":"paragraph"},{"type":"paragraph","inlineContent":[{"text":"Because a weak reference doesn’t keep a strong hold on the instance it refers to,","type":"text"},{"type":"text","text":" "},{"text":"it’s possible for that instance to be deallocated","type":"text"},{"type":"text","text":" "},{"text":"while the weak reference is still referring to it.","type":"text"},{"text":" ","type":"text"},{"text":"Therefore, ARC automatically sets a weak reference to ","type":"text"},{"code":"nil","type":"codeVoice"},{"text":" ","type":"text"},{"text":"when the instance that it refers to is deallocated.","type":"text"},{"type":"text","text":" "},{"type":"text","text":"And, because weak references need to allow"},{"type":"text","text":" "},{"type":"text","text":"their value to be changed to "},{"code":"nil","type":"codeVoice"},{"type":"text","text":" at runtime,"},{"text":" ","type":"text"},{"type":"text","text":"they’re always declared as variables, rather than constants, of an optional type."}]},{"type":"paragraph","inlineContent":[{"type":"text","text":"You can check for the existence of a value in the weak reference,"},{"text":" ","type":"text"},{"text":"just like any other optional value,","type":"text"},{"type":"text","text":" "},{"text":"and you will never end up with","type":"text"},{"type":"text","text":" "},{"text":"a reference to an invalid instance that no longer exists.","type":"text"}]},{"style":"note","type":"aside","name":"Note","content":[{"type":"paragraph","inlineContent":[{"text":"Property observers aren’t called","type":"text"},{"type":"text","text":" "},{"text":"when ARC sets a weak reference to ","type":"text"},{"type":"codeVoice","code":"nil"},{"type":"text","text":"."}]}]},{"type":"paragraph","inlineContent":[{"type":"text","text":"The example below is identical to the "},{"code":"Person","type":"codeVoice"},{"type":"text","text":" and "},{"type":"codeVoice","code":"Apartment"},{"text":" example from above,","type":"text"},{"text":" ","type":"text"},{"type":"text","text":"with one important difference."},{"type":"text","text":" "},{"text":"This time around, the ","type":"text"},{"code":"Apartment","type":"codeVoice"},{"text":" type’s ","type":"text"},{"code":"tenant","type":"codeVoice"},{"type":"text","text":" property"},{"type":"text","text":" "},{"type":"text","text":"is declared as a weak reference:"}]},{"type":"codeListing","syntax":"swift","code":["class Person {","    let name: String","    init(name: String) { self.name = name }","    var apartment: Apartment?","    deinit { print(\"\\(name) is being deinitialized\") }","}","","class Apartment {","    let unit: String","    init(unit: String) { self.unit = unit }","    weak var tenant: Person?","    deinit { print(\"Apartment \\(unit) is being deinitialized\") }","}"]},{"inlineContent":[{"text":"The strong references from the two variables (","type":"text"},{"type":"codeVoice","code":"john"},{"type":"text","text":" and "},{"code":"unit4A","type":"codeVoice"},{"text":")","type":"text"},{"type":"text","text":" "},{"text":"and the links between the two instances are created as before:","type":"text"}],"type":"paragraph"},{"type":"codeListing","code":["var john: Person?","var unit4A: Apartment?","","john = Person(name: \"John Appleseed\")","unit4A = Apartment(unit: \"4A\")","","john!.apartment = unit4A","unit4A!.tenant = john"],"syntax":"swift"},{"inlineContent":[{"type":"text","text":"Here’s how the references look now that you’ve linked the two instances together:"}],"type":"paragraph"},{"inlineContent":[{"type":"image","identifier":"weakReference01"}],"type":"paragraph"},{"inlineContent":[{"text":"The ","type":"text"},{"type":"codeVoice","code":"Person"},{"type":"text","text":" instance still has a strong reference to the "},{"code":"Apartment","type":"codeVoice"},{"text":" instance,","type":"text"},{"text":" ","type":"text"},{"type":"text","text":"but the "},{"code":"Apartment","type":"codeVoice"},{"text":" instance now has a ","type":"text"},{"type":"emphasis","inlineContent":[{"type":"text","text":"weak"}]},{"text":" reference to the ","type":"text"},{"type":"codeVoice","code":"Person"},{"type":"text","text":" instance."},{"text":" ","type":"text"},{"text":"This means that when you break the strong reference held by","type":"text"},{"text":" ","type":"text"},{"text":"the ","type":"text"},{"type":"codeVoice","code":"john"},{"type":"text","text":" variable by setting it to "},{"code":"nil","type":"codeVoice"},{"text":",","type":"text"},{"type":"text","text":" "},{"type":"text","text":"there are no more strong references to the "},{"code":"Person","type":"codeVoice"},{"type":"text","text":" instance:"}],"type":"paragraph"},{"code":["john = nil","\/\/ Prints \"John Appleseed is being deinitialized\""],"syntax":"swift","type":"codeListing"},{"type":"paragraph","inlineContent":[{"text":"Because there are no more strong references to the ","type":"text"},{"code":"Person","type":"codeVoice"},{"type":"text","text":" instance,"},{"type":"text","text":" "},{"text":"it’s deallocated","type":"text"},{"type":"text","text":" "},{"type":"text","text":"and the "},{"code":"tenant","type":"codeVoice"},{"text":" property is set to ","type":"text"},{"type":"codeVoice","code":"nil"},{"text":":","type":"text"}]},{"inlineContent":[{"identifier":"weakReference02","type":"image"}],"type":"paragraph"},{"type":"paragraph","inlineContent":[{"type":"text","text":"The only remaining strong reference to the "},{"type":"codeVoice","code":"Apartment"},{"type":"text","text":" instance"},{"type":"text","text":" "},{"type":"text","text":"is from the "},{"code":"unit4A","type":"codeVoice"},{"type":"text","text":" variable."},{"text":" ","type":"text"},{"text":"If you break ","type":"text"},{"type":"emphasis","inlineContent":[{"type":"text","text":"that"}]},{"type":"text","text":" strong reference,"},{"text":" ","type":"text"},{"type":"text","text":"there are no more strong references to the "},{"code":"Apartment","type":"codeVoice"},{"text":" instance:","type":"text"}]},{"code":["unit4A = nil","\/\/ Prints \"Apartment 4A is being deinitialized\""],"type":"codeListing","syntax":"swift"},{"type":"paragraph","inlineContent":[{"type":"text","text":"Because there are no more strong references to the "},{"code":"Apartment","type":"codeVoice"},{"text":" instance,","type":"text"},{"text":" ","type":"text"},{"type":"text","text":"it too is deallocated:"}]},{"type":"paragraph","inlineContent":[{"type":"image","identifier":"weakReference03"}]},{"style":"note","name":"Note","content":[{"inlineContent":[{"text":"In systems that use garbage collection,","type":"text"},{"type":"text","text":" "},{"text":"weak pointers are sometimes used to implement a simple caching mechanism","type":"text"},{"text":" ","type":"text"},{"type":"text","text":"because objects with no strong references are deallocated"},{"type":"text","text":" "},{"text":"only when memory pressure triggers garbage collection.","type":"text"},{"text":" ","type":"text"},{"type":"text","text":"However, with ARC, values are deallocated"},{"text":" ","type":"text"},{"text":"as soon as their last strong reference is removed,","type":"text"},{"type":"text","text":" "},{"text":"making weak references unsuitable for such a purpose.","type":"text"}],"type":"paragraph"}],"type":"aside"},{"type":"heading","level":3,"text":"Unowned References","anchor":"Unowned-References"},{"inlineContent":[{"type":"text","text":"Like a weak reference,"},{"type":"text","text":" "},{"text":"an ","type":"text"},{"type":"emphasis","inlineContent":[{"text":"unowned reference","type":"text"}]},{"type":"text","text":" doesn’t keep"},{"type":"text","text":" "},{"text":"a strong hold on the instance it refers to.","type":"text"},{"type":"text","text":" "},{"text":"Unlike a weak reference, however,","type":"text"},{"type":"text","text":" "},{"text":"an unowned reference is used when the other instance","type":"text"},{"type":"text","text":" "},{"text":"has the same lifetime or a longer lifetime.","type":"text"},{"text":" ","type":"text"},{"type":"text","text":"You indicate an unowned reference by placing the "},{"type":"codeVoice","code":"unowned"},{"text":" keyword","type":"text"},{"type":"text","text":" "},{"text":"before a property or variable declaration.","type":"text"}],"type":"paragraph"},{"type":"paragraph","inlineContent":[{"type":"text","text":"Unlike a weak reference,"},{"text":" ","type":"text"},{"text":"an unowned reference is expected to always have a value.","type":"text"},{"type":"text","text":" "},{"text":"As a result,","type":"text"},{"type":"text","text":" "},{"type":"text","text":"marking a value as unowned doesn’t make it optional,"},{"type":"text","text":" "},{"type":"text","text":"and ARC never sets an unowned reference’s value to "},{"code":"nil","type":"codeVoice"},{"type":"text","text":"."}]},{"name":"Important","content":[{"type":"paragraph","inlineContent":[{"type":"text","text":"Use an unowned reference only when you are sure that"},{"text":" ","type":"text"},{"text":"the reference ","type":"text"},{"type":"emphasis","inlineContent":[{"text":"always","type":"text"}]},{"type":"text","text":" refers to an instance that hasn’t been deallocated."}]},{"type":"paragraph","inlineContent":[{"type":"text","text":"If you try to access the value of an unowned reference"},{"type":"text","text":" "},{"text":"after that instance has been deallocated,","type":"text"},{"text":" ","type":"text"},{"type":"text","text":"you’ll get a runtime error."}]}],"style":"important","type":"aside"},{"inlineContent":[{"type":"text","text":"The following example defines two classes, "},{"type":"codeVoice","code":"Customer"},{"type":"text","text":" and "},{"type":"codeVoice","code":"CreditCard"},{"type":"text","text":","},{"text":" ","type":"text"},{"type":"text","text":"which model a bank customer and a possible credit card for that customer."},{"type":"text","text":" "},{"text":"These two classes each store an instance of the other class as a property.","type":"text"},{"type":"text","text":" "},{"type":"text","text":"This relationship has the potential to create a strong reference cycle."}],"type":"paragraph"},{"type":"paragraph","inlineContent":[{"text":"The relationship between ","type":"text"},{"type":"codeVoice","code":"Customer"},{"text":" and ","type":"text"},{"type":"codeVoice","code":"CreditCard"},{"type":"text","text":" is slightly different from"},{"text":" ","type":"text"},{"type":"text","text":"the relationship between "},{"type":"codeVoice","code":"Apartment"},{"text":" and ","type":"text"},{"code":"Person","type":"codeVoice"},{"text":" ","type":"text"},{"type":"text","text":"seen in the weak reference example above."},{"text":" ","type":"text"},{"type":"text","text":"In this data model, a customer may or may not have a credit card,"},{"text":" ","type":"text"},{"type":"text","text":"but a credit card will "},{"type":"emphasis","inlineContent":[{"type":"text","text":"always"}]},{"type":"text","text":" be associated with a customer."},{"type":"text","text":" "},{"text":"A ","type":"text"},{"code":"CreditCard","type":"codeVoice"},{"type":"text","text":" instance never outlives the "},{"type":"codeVoice","code":"Customer"},{"text":" that it refers to.","type":"text"},{"type":"text","text":" "},{"text":"To represent this, the ","type":"text"},{"type":"codeVoice","code":"Customer"},{"type":"text","text":" class has an optional "},{"type":"codeVoice","code":"card"},{"text":" property,","type":"text"},{"type":"text","text":" "},{"text":"but the ","type":"text"},{"type":"codeVoice","code":"CreditCard"},{"type":"text","text":" class has an unowned (and non-optional) "},{"type":"codeVoice","code":"customer"},{"type":"text","text":" property."}]},{"type":"paragraph","inlineContent":[{"type":"text","text":"Furthermore, a new "},{"type":"codeVoice","code":"CreditCard"},{"type":"text","text":" instance can "},{"inlineContent":[{"type":"text","text":"only"}],"type":"emphasis"},{"text":" be created","type":"text"},{"type":"text","text":" "},{"type":"text","text":"by passing a "},{"type":"codeVoice","code":"number"},{"type":"text","text":" value and a "},{"type":"codeVoice","code":"customer"},{"text":" instance","type":"text"},{"text":" ","type":"text"},{"text":"to a custom ","type":"text"},{"type":"codeVoice","code":"CreditCard"},{"text":" initializer.","type":"text"},{"type":"text","text":" "},{"text":"This ensures that a ","type":"text"},{"code":"CreditCard","type":"codeVoice"},{"type":"text","text":" instance always has"},{"text":" ","type":"text"},{"type":"text","text":"a "},{"code":"customer","type":"codeVoice"},{"type":"text","text":" instance associated with it when the "},{"type":"codeVoice","code":"CreditCard"},{"text":" instance is created.","type":"text"}]},{"type":"paragraph","inlineContent":[{"text":"Because a credit card will always have a customer,","type":"text"},{"type":"text","text":" "},{"type":"text","text":"you define its "},{"type":"codeVoice","code":"customer"},{"text":" property as an unowned reference,","type":"text"},{"text":" ","type":"text"},{"text":"to avoid a strong reference cycle:","type":"text"}]},{"syntax":"swift","code":["class Customer {","    let name: String","    var card: CreditCard?","    init(name: String) {","        self.name = name","    }","    deinit { print(\"\\(name) is being deinitialized\") }","}","","class CreditCard {","    let number: UInt64","    unowned let customer: Customer","    init(number: UInt64, customer: Customer) {","        self.number = number","        self.customer = customer","    }","    deinit { print(\"Card #\\(number) is being deinitialized\") }","}"],"type":"codeListing"},{"type":"aside","content":[{"inlineContent":[{"text":"The ","type":"text"},{"type":"codeVoice","code":"number"},{"text":" property of the ","type":"text"},{"type":"codeVoice","code":"CreditCard"},{"text":" class is defined with","type":"text"},{"type":"text","text":" "},{"text":"a type of ","type":"text"},{"type":"codeVoice","code":"UInt64"},{"type":"text","text":" rather than "},{"type":"codeVoice","code":"Int"},{"type":"text","text":","},{"text":" ","type":"text"},{"text":"to ensure that the ","type":"text"},{"code":"number","type":"codeVoice"},{"type":"text","text":" property’s capacity is large enough to store"},{"type":"text","text":" "},{"text":"a 16-digit card number on both 32-bit and 64-bit systems.","type":"text"}],"type":"paragraph"}],"style":"note","name":"Note"},{"type":"paragraph","inlineContent":[{"text":"This next code snippet defines an optional ","type":"text"},{"code":"Customer","type":"codeVoice"},{"type":"text","text":" variable called "},{"code":"john","type":"codeVoice"},{"type":"text","text":","},{"type":"text","text":" "},{"type":"text","text":"which will be used to store a reference to a specific customer."},{"type":"text","text":" "},{"type":"text","text":"This variable has an initial value of nil, by virtue of being optional:"}]},{"type":"codeListing","code":["var john: Customer?"],"syntax":"swift"},{"inlineContent":[{"text":"You can now create a ","type":"text"},{"type":"codeVoice","code":"Customer"},{"type":"text","text":" instance,"},{"type":"text","text":" "},{"type":"text","text":"and use it to initialize and assign a new "},{"code":"CreditCard","type":"codeVoice"},{"text":" instance","type":"text"},{"type":"text","text":" "},{"type":"text","text":"as that customer’s "},{"type":"codeVoice","code":"card"},{"text":" property:","type":"text"}],"type":"paragraph"},{"code":["john = Customer(name: \"John Appleseed\")","john!.card = CreditCard(number: 1234_5678_9012_3456, customer: john!)"],"syntax":"swift","type":"codeListing"},{"type":"paragraph","inlineContent":[{"text":"Here’s how the references look, now that you’ve linked the two instances:","type":"text"}]},{"type":"paragraph","inlineContent":[{"type":"image","identifier":"unownedReference01"}]},{"inlineContent":[{"type":"text","text":"The "},{"code":"Customer","type":"codeVoice"},{"text":" instance now has a strong reference to the ","type":"text"},{"code":"CreditCard","type":"codeVoice"},{"type":"text","text":" instance,"},{"type":"text","text":" "},{"type":"text","text":"and the "},{"code":"CreditCard","type":"codeVoice"},{"text":" instance has an unowned reference to the ","type":"text"},{"type":"codeVoice","code":"Customer"},{"type":"text","text":" instance."}],"type":"paragraph"},{"type":"paragraph","inlineContent":[{"type":"text","text":"Because of the unowned "},{"type":"codeVoice","code":"customer"},{"type":"text","text":" reference,"},{"type":"text","text":" "},{"type":"text","text":"when you break the strong reference held by the "},{"code":"john","type":"codeVoice"},{"text":" variable,","type":"text"},{"type":"text","text":" "},{"text":"there are no more strong references to the ","type":"text"},{"type":"codeVoice","code":"Customer"},{"text":" instance:","type":"text"}]},{"inlineContent":[{"identifier":"unownedReference02","type":"image"}],"type":"paragraph"},{"inlineContent":[{"text":"Because there are no more strong references to the ","type":"text"},{"type":"codeVoice","code":"Customer"},{"text":" instance,","type":"text"},{"type":"text","text":" "},{"type":"text","text":"it’s deallocated."},{"type":"text","text":" "},{"text":"After this happens,","type":"text"},{"type":"text","text":" "},{"type":"text","text":"there are no more strong references to the "},{"code":"CreditCard","type":"codeVoice"},{"text":" instance,","type":"text"},{"type":"text","text":" "},{"text":"and it too is deallocated:","type":"text"}],"type":"paragraph"},{"type":"codeListing","code":["john = nil","\/\/ Prints \"John Appleseed is being deinitialized\"","\/\/ Prints \"Card #1234567890123456 is being deinitialized\""],"syntax":"swift"},{"type":"paragraph","inlineContent":[{"type":"text","text":"The final code snippet above shows that"},{"text":" ","type":"text"},{"type":"text","text":"the deinitializers for the "},{"type":"codeVoice","code":"Customer"},{"type":"text","text":" instance and "},{"code":"CreditCard","type":"codeVoice"},{"type":"text","text":" instance"},{"text":" ","type":"text"},{"type":"text","text":"both print their “deinitialized” messages"},{"type":"text","text":" "},{"type":"text","text":"after the "},{"type":"codeVoice","code":"john"},{"type":"text","text":" variable is set to "},{"type":"codeVoice","code":"nil"},{"text":".","type":"text"}]},{"content":[{"type":"paragraph","inlineContent":[{"type":"text","text":"The examples above show how to use "},{"type":"emphasis","inlineContent":[{"text":"safe","type":"text"}]},{"type":"text","text":" unowned references."},{"type":"text","text":" "},{"type":"text","text":"Swift also provides "},{"inlineContent":[{"type":"text","text":"unsafe"}],"type":"emphasis"},{"text":" unowned references for cases where","type":"text"},{"type":"text","text":" "},{"text":"you need to disable runtime safety checks —","type":"text"},{"type":"text","text":" "},{"text":"for example, for performance reasons.","type":"text"},{"type":"text","text":" "},{"type":"text","text":"As with all unsafe operations,"},{"text":" ","type":"text"},{"text":"you take on the responsibility for checking that code for safety.","type":"text"}]},{"inlineContent":[{"type":"text","text":"You indicate an unsafe unowned reference by writing "},{"code":"unowned(unsafe)","type":"codeVoice"},{"text":".","type":"text"},{"type":"text","text":" "},{"type":"text","text":"If you try to access an unsafe unowned reference"},{"text":" ","type":"text"},{"type":"text","text":"after the instance that it refers to is deallocated,"},{"type":"text","text":" "},{"type":"text","text":"your program will try to access the memory location"},{"text":" ","type":"text"},{"text":"where the instance used to be,","type":"text"},{"text":" ","type":"text"},{"type":"text","text":"which is an unsafe operation."}],"type":"paragraph"}],"name":"Note","style":"note","type":"aside"},{"text":"Unowned Optional References","type":"heading","level":3,"anchor":"Unowned-Optional-References"},{"inlineContent":[{"text":"You can mark an optional reference to a class as unowned.","type":"text"},{"type":"text","text":" "},{"text":"In terms of the ARC ownership model,","type":"text"},{"type":"text","text":" "},{"text":"an unowned optional reference and a weak reference","type":"text"},{"type":"text","text":" "},{"text":"can both be used in the same contexts.","type":"text"},{"text":" ","type":"text"},{"type":"text","text":"The difference is that when you use an unowned optional reference,"},{"type":"text","text":" "},{"text":"you’re responsible for making sure it always","type":"text"},{"text":" ","type":"text"},{"text":"refers to a valid object or is set to ","type":"text"},{"code":"nil","type":"codeVoice"},{"type":"text","text":"."}],"type":"paragraph"},{"type":"paragraph","inlineContent":[{"text":"Here’s an example that keeps track of the courses","type":"text"},{"text":" ","type":"text"},{"type":"text","text":"offered by a particular department at a school:"}]},{"code":["class Department {","    var name: String","    var courses: [Course]","    init(name: String) {","        self.name = name","        self.courses = []","    }","}","","class Course {","    var name: String","    unowned var department: Department","    unowned var nextCourse: Course?","    init(name: String, in department: Department) {","        self.name = name","        self.department = department","        self.nextCourse = nil","    }","}"],"syntax":"swift","type":"codeListing"},{"type":"paragraph","inlineContent":[{"code":"Department","type":"codeVoice"},{"text":" maintains a strong reference","type":"text"},{"type":"text","text":" "},{"text":"to each course that the department offers.","type":"text"},{"text":" ","type":"text"},{"type":"text","text":"In the ARC ownership model, a department owns its courses."},{"type":"text","text":" "},{"type":"codeVoice","code":"Course"},{"type":"text","text":" has two unowned references,"},{"text":" ","type":"text"},{"type":"text","text":"one to the department"},{"text":" ","type":"text"},{"text":"and one to the next course a student should take;","type":"text"},{"text":" ","type":"text"},{"type":"text","text":"a course doesn’t own either of these objects."},{"text":" ","type":"text"},{"type":"text","text":"Every course is part of some department"},{"text":" ","type":"text"},{"text":"so the ","type":"text"},{"code":"department","type":"codeVoice"},{"type":"text","text":" property isn’t an optional."},{"type":"text","text":" "},{"type":"text","text":"However,"},{"text":" ","type":"text"},{"type":"text","text":"because some courses don’t have a recommended follow-on course,"},{"type":"text","text":" "},{"text":"the ","type":"text"},{"code":"nextCourse","type":"codeVoice"},{"type":"text","text":" property is an optional."}]},{"inlineContent":[{"type":"text","text":"Here’s an example of using these classes:"}],"type":"paragraph"},{"syntax":"swift","type":"codeListing","code":["let department = Department(name: \"Horticulture\")","","let intro = Course(name: \"Survey of Plants\", in: department)","let intermediate = Course(name: \"Growing Common Herbs\", in: department)","let advanced = Course(name: \"Caring for Tropical Plants\", in: department)","","intro.nextCourse = intermediate","intermediate.nextCourse = advanced","department.courses = [intro, intermediate, advanced]"]},{"type":"paragraph","inlineContent":[{"type":"text","text":"The code above creates a department and its three courses."},{"text":" ","type":"text"},{"text":"The intro and intermediate courses both have a suggested next course","type":"text"},{"text":" ","type":"text"},{"text":"stored in their ","type":"text"},{"code":"nextCourse","type":"codeVoice"},{"type":"text","text":" property,"},{"type":"text","text":" "},{"type":"text","text":"which maintains an unowned optional reference to"},{"text":" ","type":"text"},{"type":"text","text":"the course a student should take after completing this one."}]},{"type":"paragraph","inlineContent":[{"identifier":"unownedOptionalReference","type":"image"}]},{"inlineContent":[{"type":"text","text":"An unowned optional reference doesn’t keep a strong hold"},{"type":"text","text":" "},{"text":"on the instance of the class that it wraps,","type":"text"},{"type":"text","text":" "},{"text":"and so it doesn’t prevent ARC from deallocating the instance.","type":"text"},{"type":"text","text":" "},{"type":"text","text":"It behaves the same as an unowned reference does under ARC,"},{"text":" ","type":"text"},{"type":"text","text":"except that an unowned optional reference can be "},{"code":"nil","type":"codeVoice"},{"text":".","type":"text"}],"type":"paragraph"},{"type":"paragraph","inlineContent":[{"text":"Like non-optional unowned references,","type":"text"},{"text":" ","type":"text"},{"type":"text","text":"you’re responsible for ensuring that "},{"code":"nextCourse","type":"codeVoice"},{"text":" ","type":"text"},{"type":"text","text":"always refers to a course that hasn’t been deallocated."},{"text":" ","type":"text"},{"type":"text","text":"In this case, for example,"},{"text":" ","type":"text"},{"text":"when you delete a course from ","type":"text"},{"code":"department.courses","type":"codeVoice"},{"type":"text","text":" "},{"text":"you also need to remove any references to it","type":"text"},{"text":" ","type":"text"},{"text":"that other courses might have.","type":"text"}]},{"name":"Note","type":"aside","style":"note","content":[{"inlineContent":[{"text":"The underlying type of an optional value is ","type":"text"},{"code":"Optional","type":"codeVoice"},{"type":"text","text":","},{"type":"text","text":" "},{"type":"text","text":"which is an enumeration in the Swift standard library."},{"type":"text","text":" "},{"type":"text","text":"However, optionals are an exception to the rule that"},{"type":"text","text":" "},{"type":"text","text":"value types can’t be marked with "},{"type":"codeVoice","code":"unowned"},{"type":"text","text":"."}],"type":"paragraph"},{"type":"paragraph","inlineContent":[{"type":"text","text":"The optional that wraps the class"},{"text":" ","type":"text"},{"type":"text","text":"doesn’t use reference counting,"},{"type":"text","text":" "},{"text":"so you don’t need to maintain a strong reference to the optional.","type":"text"}]}]},{"text":"Unowned References and Implicitly Unwrapped Optional Properties","anchor":"Unowned-References-and-Implicitly-Unwrapped-Optional-Properties","level":3,"type":"heading"},{"type":"paragraph","inlineContent":[{"type":"text","text":"The examples for weak and unowned references above"},{"type":"text","text":" "},{"type":"text","text":"cover two of the more common scenarios"},{"type":"text","text":" "},{"type":"text","text":"in which it’s necessary to break a strong reference cycle."}]},{"type":"paragraph","inlineContent":[{"text":"The ","type":"text"},{"type":"codeVoice","code":"Person"},{"type":"text","text":" and "},{"code":"Apartment","type":"codeVoice"},{"text":" example shows","type":"text"},{"text":" ","type":"text"},{"type":"text","text":"a situation where two properties, both of which are allowed to be "},{"type":"codeVoice","code":"nil"},{"text":",","type":"text"},{"type":"text","text":" "},{"text":"have the potential to cause a strong reference cycle.","type":"text"},{"text":" ","type":"text"},{"type":"text","text":"This scenario is best resolved with a weak reference."}]},{"inlineContent":[{"type":"text","text":"The "},{"code":"Customer","type":"codeVoice"},{"text":" and ","type":"text"},{"type":"codeVoice","code":"CreditCard"},{"text":" example","type":"text"},{"text":" ","type":"text"},{"type":"text","text":"shows a situation where one property that’s allowed to be "},{"code":"nil","type":"codeVoice"},{"type":"text","text":" "},{"text":"and another property that can’t be ","type":"text"},{"code":"nil","type":"codeVoice"},{"text":" ","type":"text"},{"type":"text","text":"have the potential to cause a strong reference cycle."},{"text":" ","type":"text"},{"type":"text","text":"This scenario is best resolved with an unowned reference."}],"type":"paragraph"},{"type":"paragraph","inlineContent":[{"type":"text","text":"However, there’s a third scenario,"},{"type":"text","text":" "},{"text":"in which ","type":"text"},{"inlineContent":[{"type":"text","text":"both"}],"type":"emphasis"},{"text":" properties should always have a value,","type":"text"},{"text":" ","type":"text"},{"type":"text","text":"and neither property should ever be "},{"type":"codeVoice","code":"nil"},{"type":"text","text":" once initialization is complete."},{"type":"text","text":" "},{"text":"In this scenario, it’s useful to combine an unowned property on one class","type":"text"},{"text":" ","type":"text"},{"text":"with an implicitly unwrapped optional property on the other class.","type":"text"}]},{"type":"paragraph","inlineContent":[{"type":"text","text":"This enables both properties to be accessed directly"},{"type":"text","text":" "},{"type":"text","text":"(without optional unwrapping) once initialization is complete,"},{"text":" ","type":"text"},{"text":"while still avoiding a reference cycle.","type":"text"},{"type":"text","text":" "},{"type":"text","text":"This section shows you how to set up such a relationship."}]},{"type":"paragraph","inlineContent":[{"text":"The example below defines two classes, ","type":"text"},{"type":"codeVoice","code":"Country"},{"text":" and ","type":"text"},{"type":"codeVoice","code":"City"},{"type":"text","text":","},{"type":"text","text":" "},{"text":"each of which stores an instance of the other class as a property.","type":"text"},{"type":"text","text":" "},{"type":"text","text":"In this data model, every country must always have a capital city,"},{"text":" ","type":"text"},{"text":"and every city must always belong to a country.","type":"text"},{"type":"text","text":" "},{"type":"text","text":"To represent this, the "},{"type":"codeVoice","code":"Country"},{"text":" class has a ","type":"text"},{"type":"codeVoice","code":"capitalCity"},{"text":" property,","type":"text"},{"text":" ","type":"text"},{"type":"text","text":"and the "},{"code":"City","type":"codeVoice"},{"type":"text","text":" class has a "},{"code":"country","type":"codeVoice"},{"text":" property:","type":"text"}]},{"type":"codeListing","code":["class Country {","    let name: String","    var capitalCity: City!","    init(name: String, capitalName: String) {","        self.name = name","        self.capitalCity = City(name: capitalName, country: self)","    }","}","","class City {","    let name: String","    unowned let country: Country","    init(name: String, country: Country) {","        self.name = name","        self.country = country","    }","}"],"syntax":"swift"},{"inlineContent":[{"type":"text","text":"To set up the interdependency between the two classes,"},{"type":"text","text":" "},{"type":"text","text":"the initializer for "},{"code":"City","type":"codeVoice"},{"text":" takes a ","type":"text"},{"code":"Country","type":"codeVoice"},{"type":"text","text":" instance,"},{"type":"text","text":" "},{"text":"and stores this instance in its ","type":"text"},{"type":"codeVoice","code":"country"},{"text":" property.","type":"text"}],"type":"paragraph"},{"inlineContent":[{"text":"The initializer for ","type":"text"},{"type":"codeVoice","code":"City"},{"type":"text","text":" is called from within the initializer for "},{"type":"codeVoice","code":"Country"},{"type":"text","text":"."},{"type":"text","text":" "},{"text":"However, the initializer for ","type":"text"},{"type":"codeVoice","code":"Country"},{"type":"text","text":" can’t pass "},{"code":"self","type":"codeVoice"},{"text":" to the ","type":"text"},{"code":"City","type":"codeVoice"},{"text":" initializer","type":"text"},{"text":" ","type":"text"},{"text":"until a new ","type":"text"},{"code":"Country","type":"codeVoice"},{"type":"text","text":" instance is fully initialized,"},{"text":" ","type":"text"},{"type":"text","text":"as described in "},{"type":"reference","identifier":"doc:\/\/org.swift.tspl\/documentation\/The-Swift-Programming-Language\/Initialization#Two-Phase-Initialization","isActive":true},{"text":".","type":"text"}],"type":"paragraph"},{"inlineContent":[{"type":"text","text":"To cope with this requirement,"},{"text":" ","type":"text"},{"type":"text","text":"you declare the "},{"type":"codeVoice","code":"capitalCity"},{"type":"text","text":" property of "},{"type":"codeVoice","code":"Country"},{"type":"text","text":" as"},{"text":" ","type":"text"},{"text":"an implicitly unwrapped optional property,","type":"text"},{"text":" ","type":"text"},{"type":"text","text":"indicated by the exclamation point at the end of its type annotation ("},{"code":"City!","type":"codeVoice"},{"type":"text","text":")."},{"text":" ","type":"text"},{"type":"text","text":"This means that the "},{"type":"codeVoice","code":"capitalCity"},{"type":"text","text":" property has a default value of "},{"code":"nil","type":"codeVoice"},{"text":",","type":"text"},{"type":"text","text":" "},{"text":"like any other optional,","type":"text"},{"type":"text","text":" "},{"type":"text","text":"but can be accessed without the need to unwrap its value"},{"type":"text","text":" "},{"type":"text","text":"as described in "},{"type":"reference","isActive":true,"identifier":"doc:\/\/org.swift.tspl\/documentation\/The-Swift-Programming-Language\/TheBasics#Implicitly-Unwrapped-Optionals"},{"text":".","type":"text"}],"type":"paragraph"},{"type":"paragraph","inlineContent":[{"type":"text","text":"Because "},{"code":"capitalCity","type":"codeVoice"},{"text":" has a default ","type":"text"},{"code":"nil","type":"codeVoice"},{"type":"text","text":" value,"},{"type":"text","text":" "},{"type":"text","text":"a new "},{"type":"codeVoice","code":"Country"},{"text":" instance is considered fully initialized","type":"text"},{"type":"text","text":" "},{"type":"text","text":"as soon as the "},{"code":"Country","type":"codeVoice"},{"type":"text","text":" instance sets its "},{"code":"name","type":"codeVoice"},{"text":" property within its initializer.","type":"text"},{"type":"text","text":" "},{"type":"text","text":"This means that the "},{"type":"codeVoice","code":"Country"},{"type":"text","text":" initializer can start to reference and pass around"},{"type":"text","text":" "},{"type":"text","text":"the implicit "},{"code":"self","type":"codeVoice"},{"type":"text","text":" property as soon as the "},{"type":"codeVoice","code":"name"},{"text":" property is set.","type":"text"},{"type":"text","text":" "},{"type":"text","text":"The "},{"code":"Country","type":"codeVoice"},{"type":"text","text":" initializer can therefore pass "},{"code":"self","type":"codeVoice"},{"text":" as one of the parameters for","type":"text"},{"text":" ","type":"text"},{"type":"text","text":"the "},{"code":"City","type":"codeVoice"},{"type":"text","text":" initializer when the "},{"code":"Country","type":"codeVoice"},{"type":"text","text":" initializer is setting"},{"type":"text","text":" "},{"text":"its own ","type":"text"},{"type":"codeVoice","code":"capitalCity"},{"text":" property.","type":"text"}]},{"type":"paragraph","inlineContent":[{"text":"All of this means that you can create the ","type":"text"},{"type":"codeVoice","code":"Country"},{"type":"text","text":" and "},{"type":"codeVoice","code":"City"},{"type":"text","text":" instances"},{"text":" ","type":"text"},{"type":"text","text":"in a single statement, without creating a strong reference cycle,"},{"type":"text","text":" "},{"type":"text","text":"and the "},{"type":"codeVoice","code":"capitalCity"},{"text":" property can be accessed directly,","type":"text"},{"text":" ","type":"text"},{"type":"text","text":"without needing to use an exclamation point to unwrap its optional value:"}]},{"syntax":"swift","code":["var country = Country(name: \"Canada\", capitalName: \"Ottawa\")","print(\"\\(country.name)'s capital city is called \\(country.capitalCity.name)\")","\/\/ Prints \"Canada's capital city is called Ottawa\""],"type":"codeListing"},{"inlineContent":[{"type":"text","text":"In the example above, the use of an implicitly unwrapped optional"},{"type":"text","text":" "},{"text":"means that all of the two-phase class initializer requirements are satisfied.","type":"text"},{"type":"text","text":" "},{"text":"The ","type":"text"},{"code":"capitalCity","type":"codeVoice"},{"type":"text","text":" property can be used and accessed like a non-optional value"},{"type":"text","text":" "},{"type":"text","text":"once initialization is complete,"},{"type":"text","text":" "},{"type":"text","text":"while still avoiding a strong reference cycle."}],"type":"paragraph"},{"type":"heading","level":2,"anchor":"Strong-Reference-Cycles-for-Closures","text":"Strong Reference Cycles for Closures"},{"type":"paragraph","inlineContent":[{"type":"text","text":"You saw above how a strong reference cycle can be created"},{"type":"text","text":" "},{"text":"when two class instance properties hold a strong reference to each other.","type":"text"},{"text":" ","type":"text"},{"type":"text","text":"You also saw how to use weak and unowned references to break these strong reference cycles."}]},{"inlineContent":[{"text":"A strong reference cycle can also occur","type":"text"},{"type":"text","text":" "},{"type":"text","text":"if you assign a closure to a property of a class instance,"},{"type":"text","text":" "},{"text":"and the body of that closure captures the instance.","type":"text"},{"type":"text","text":" "},{"text":"This capture might occur because the closure’s body accesses a property of the instance,","type":"text"},{"type":"text","text":" "},{"type":"text","text":"such as "},{"code":"self.someProperty","type":"codeVoice"},{"type":"text","text":","},{"type":"text","text":" "},{"type":"text","text":"or because the closure calls a method on the instance,"},{"text":" ","type":"text"},{"text":"such as ","type":"text"},{"code":"self.someMethod()","type":"codeVoice"},{"text":".","type":"text"},{"type":"text","text":" "},{"type":"text","text":"In either case, these accesses cause the closure to “capture” "},{"type":"codeVoice","code":"self"},{"type":"text","text":","},{"text":" ","type":"text"},{"text":"creating a strong reference cycle.","type":"text"}],"type":"paragraph"},{"inlineContent":[{"text":"This strong reference cycle occurs because closures, like classes, are ","type":"text"},{"inlineContent":[{"text":"reference types","type":"text"}],"type":"emphasis"},{"text":".","type":"text"},{"text":" ","type":"text"},{"type":"text","text":"When you assign a closure to a property,"},{"type":"text","text":" "},{"text":"you are assigning a ","type":"text"},{"type":"emphasis","inlineContent":[{"type":"text","text":"reference"}]},{"type":"text","text":" to that closure."},{"type":"text","text":" "},{"text":"In essence, it’s the same problem as above —","type":"text"},{"type":"text","text":" "},{"type":"text","text":"two strong references are keeping each other alive."},{"text":" ","type":"text"},{"type":"text","text":"However, rather than two class instances,"},{"type":"text","text":" "},{"text":"this time it’s a class instance and a closure that are keeping each other alive.","type":"text"}],"type":"paragraph"},{"inlineContent":[{"type":"text","text":"Swift provides an elegant solution to this problem,"},{"type":"text","text":" "},{"type":"text","text":"known as a "},{"inlineContent":[{"type":"text","text":"closure capture list"}],"type":"emphasis"},{"type":"text","text":"."},{"type":"text","text":" "},{"type":"text","text":"However, before you learn how to break a strong reference cycle with a closure capture list,"},{"type":"text","text":" "},{"text":"it’s useful to understand how such a cycle can be caused.","type":"text"}],"type":"paragraph"},{"type":"paragraph","inlineContent":[{"text":"The example below shows how you can create a strong reference cycle","type":"text"},{"text":" ","type":"text"},{"type":"text","text":"when using a closure that references "},{"type":"codeVoice","code":"self"},{"text":".","type":"text"},{"text":" ","type":"text"},{"type":"text","text":"This example defines a class called "},{"type":"codeVoice","code":"HTMLElement"},{"type":"text","text":","},{"type":"text","text":" "},{"text":"which provides a simple model for an individual element within an HTML document:","type":"text"}]},{"syntax":"swift","code":["class HTMLElement {","","    let name: String","    let text: String?","","    lazy var asHTML: () -> String = {","        if let text = self.text {","            return \"<\\(self.name)>\\(text)<\/\\(self.name)>\"","        } else {","            return \"<\\(self.name) \/>\"","        }","    }","","    init(name: String, text: String? = nil) {","        self.name = name","        self.text = text","    }","","    deinit {","        print(\"\\(name) is being deinitialized\")","    }","","}"],"type":"codeListing"},{"inlineContent":[{"type":"text","text":"The "},{"code":"HTMLElement","type":"codeVoice"},{"type":"text","text":" class defines a "},{"code":"name","type":"codeVoice"},{"text":" property,","type":"text"},{"text":" ","type":"text"},{"text":"which indicates the name of the element,","type":"text"},{"type":"text","text":" "},{"text":"such as ","type":"text"},{"code":"\"h1\"","type":"codeVoice"},{"type":"text","text":" for a heading element,"},{"type":"text","text":" "},{"code":"\"p\"","type":"codeVoice"},{"type":"text","text":" for a paragraph element,"},{"type":"text","text":" "},{"text":"or ","type":"text"},{"type":"codeVoice","code":"\"br\""},{"text":" for a line break element.","type":"text"},{"type":"text","text":" "},{"code":"HTMLElement","type":"codeVoice"},{"type":"text","text":" also defines an optional "},{"code":"text","type":"codeVoice"},{"text":" property,","type":"text"},{"type":"text","text":" "},{"type":"text","text":"which you can set to a string that represents"},{"type":"text","text":" "},{"text":"the text to be rendered within that HTML element.","type":"text"}],"type":"paragraph"},{"inlineContent":[{"text":"In addition to these two simple properties,","type":"text"},{"type":"text","text":" "},{"text":"the ","type":"text"},{"code":"HTMLElement","type":"codeVoice"},{"type":"text","text":" class defines a lazy property called "},{"type":"codeVoice","code":"asHTML"},{"type":"text","text":"."},{"type":"text","text":" "},{"type":"text","text":"This property references a closure that combines "},{"type":"codeVoice","code":"name"},{"type":"text","text":" and "},{"type":"codeVoice","code":"text"},{"type":"text","text":" "},{"type":"text","text":"into an HTML string fragment."},{"type":"text","text":" "},{"text":"The ","type":"text"},{"code":"asHTML","type":"codeVoice"},{"type":"text","text":" property is of type "},{"type":"codeVoice","code":"() -> String"},{"text":",","type":"text"},{"text":" ","type":"text"},{"type":"text","text":"or “a function that takes no parameters, and returns a "},{"type":"codeVoice","code":"String"},{"type":"text","text":" value”."}],"type":"paragraph"},{"type":"paragraph","inlineContent":[{"text":"By default, the ","type":"text"},{"type":"codeVoice","code":"asHTML"},{"text":" property is assigned a closure that returns","type":"text"},{"type":"text","text":" "},{"text":"a string representation of an HTML tag.","type":"text"},{"type":"text","text":" "},{"type":"text","text":"This tag contains the optional "},{"code":"text","type":"codeVoice"},{"text":" value if it exists,","type":"text"},{"type":"text","text":" "},{"type":"text","text":"or no text content if "},{"code":"text","type":"codeVoice"},{"type":"text","text":" doesn’t exist."},{"type":"text","text":" "},{"type":"text","text":"For a paragraph element, the closure would return "},{"code":"\"<p>some text<\/p>\"","type":"codeVoice"},{"type":"text","text":" or "},{"code":"\"<p \/>\"","type":"codeVoice"},{"type":"text","text":","},{"text":" ","type":"text"},{"type":"text","text":"depending on whether the "},{"type":"codeVoice","code":"text"},{"text":" property equals ","type":"text"},{"code":"\"some text\"","type":"codeVoice"},{"type":"text","text":" or "},{"type":"codeVoice","code":"nil"},{"text":".","type":"text"}]},{"type":"paragraph","inlineContent":[{"type":"text","text":"The "},{"type":"codeVoice","code":"asHTML"},{"text":" property is named and used somewhat like an instance method.","type":"text"},{"text":" ","type":"text"},{"type":"text","text":"However, because "},{"type":"codeVoice","code":"asHTML"},{"type":"text","text":" is a closure property rather than an instance method,"},{"type":"text","text":" "},{"type":"text","text":"you can replace the default value of the "},{"code":"asHTML","type":"codeVoice"},{"type":"text","text":" property with a custom closure,"},{"type":"text","text":" "},{"type":"text","text":"if you want to change the HTML rendering for a particular HTML element."}]},{"type":"paragraph","inlineContent":[{"type":"text","text":"For example, the "},{"code":"asHTML","type":"codeVoice"},{"type":"text","text":" property could be set to a closure"},{"text":" ","type":"text"},{"text":"that defaults to some text if the ","type":"text"},{"type":"codeVoice","code":"text"},{"type":"text","text":" property is "},{"code":"nil","type":"codeVoice"},{"type":"text","text":","},{"text":" ","type":"text"},{"text":"in order to prevent the representation from returning an empty HTML tag:","type":"text"}]},{"type":"codeListing","syntax":"swift","code":["let heading = HTMLElement(name: \"h1\")","let defaultText = \"some default text\"","heading.asHTML = {","    return \"<\\(heading.name)>\\(heading.text ?? defaultText)<\/\\(heading.name)>\"","}","print(heading.asHTML())","\/\/ Prints \"<h1>some default text<\/h1>\""]},{"style":"note","type":"aside","content":[{"inlineContent":[{"type":"text","text":"The "},{"code":"asHTML","type":"codeVoice"},{"type":"text","text":" property is declared as a lazy property,"},{"type":"text","text":" "},{"type":"text","text":"because it’s only needed if and when the element actually needs to be rendered"},{"type":"text","text":" "},{"type":"text","text":"as a string value for some HTML output target."},{"type":"text","text":" "},{"type":"text","text":"The fact that "},{"code":"asHTML","type":"codeVoice"},{"text":" is a lazy property means that you can refer to ","type":"text"},{"code":"self","type":"codeVoice"},{"text":" ","type":"text"},{"type":"text","text":"within the default closure,"},{"type":"text","text":" "},{"text":"because the lazy property will not be accessed until","type":"text"},{"type":"text","text":" "},{"type":"text","text":"after initialization has been completed and "},{"type":"codeVoice","code":"self"},{"text":" is known to exist.","type":"text"}],"type":"paragraph"}],"name":"Note"},{"type":"paragraph","inlineContent":[{"type":"text","text":"The "},{"code":"HTMLElement","type":"codeVoice"},{"text":" class provides a single initializer,","type":"text"},{"text":" ","type":"text"},{"type":"text","text":"which takes a "},{"code":"name","type":"codeVoice"},{"type":"text","text":" argument and (if desired) a "},{"type":"codeVoice","code":"text"},{"type":"text","text":" argument"},{"text":" ","type":"text"},{"type":"text","text":"to initialize a new element."},{"text":" ","type":"text"},{"text":"The class also defines a deinitializer,","type":"text"},{"type":"text","text":" "},{"type":"text","text":"which prints a message to show when an "},{"code":"HTMLElement","type":"codeVoice"},{"text":" instance is deallocated.","type":"text"}]},{"type":"paragraph","inlineContent":[{"type":"text","text":"Here’s how you use the "},{"code":"HTMLElement","type":"codeVoice"},{"text":" class to create and print a new instance:","type":"text"}]},{"type":"codeListing","syntax":"swift","code":["var paragraph: HTMLElement? = HTMLElement(name: \"p\", text: \"hello, world\")","print(paragraph!.asHTML())","\/\/ Prints \"<p>hello, world<\/p>\""]},{"style":"note","name":"Note","type":"aside","content":[{"inlineContent":[{"type":"text","text":"The "},{"type":"codeVoice","code":"paragraph"},{"type":"text","text":" variable above is defined as an "},{"type":"emphasis","inlineContent":[{"text":"optional","type":"text"}]},{"text":" ","type":"text"},{"type":"codeVoice","code":"HTMLElement"},{"text":",","type":"text"},{"type":"text","text":" "},{"type":"text","text":"so that it can be set to "},{"code":"nil","type":"codeVoice"},{"type":"text","text":" below to demonstrate"},{"type":"text","text":" "},{"type":"text","text":"the presence of a strong reference cycle."}],"type":"paragraph"}]},{"inlineContent":[{"text":"Unfortunately, the ","type":"text"},{"code":"HTMLElement","type":"codeVoice"},{"text":" class, as written above,","type":"text"},{"type":"text","text":" "},{"text":"creates a strong reference cycle between","type":"text"},{"type":"text","text":" "},{"text":"an ","type":"text"},{"type":"codeVoice","code":"HTMLElement"},{"text":" instance and the closure used for its default ","type":"text"},{"type":"codeVoice","code":"asHTML"},{"text":" value.","type":"text"},{"text":" ","type":"text"},{"type":"text","text":"Here’s how the cycle looks:"}],"type":"paragraph"},{"type":"paragraph","inlineContent":[{"identifier":"closureReferenceCycle01","type":"image"}]},{"inlineContent":[{"type":"text","text":"The instance’s "},{"type":"codeVoice","code":"asHTML"},{"type":"text","text":" property holds a strong reference to its closure."},{"type":"text","text":" "},{"type":"text","text":"However, because the closure refers to "},{"type":"codeVoice","code":"self"},{"type":"text","text":" within its body"},{"type":"text","text":" "},{"type":"text","text":"(as a way to reference "},{"code":"self.name","type":"codeVoice"},{"text":" and ","type":"text"},{"code":"self.text","type":"codeVoice"},{"type":"text","text":"),"},{"type":"text","text":" "},{"text":"the closure ","type":"text"},{"type":"emphasis","inlineContent":[{"type":"text","text":"captures"}]},{"type":"text","text":" self,"},{"type":"text","text":" "},{"text":"which means that it holds a strong reference back to the ","type":"text"},{"type":"codeVoice","code":"HTMLElement"},{"type":"text","text":" instance."},{"text":" ","type":"text"},{"text":"A strong reference cycle is created between the two.","type":"text"},{"type":"text","text":" "},{"text":"(For more information about capturing values in a closure,","type":"text"},{"text":" ","type":"text"},{"type":"text","text":"see "},{"identifier":"doc:\/\/org.swift.tspl\/documentation\/The-Swift-Programming-Language\/Closures#Capturing-Values","isActive":true,"type":"reference"},{"text":".)","type":"text"}],"type":"paragraph"},{"name":"Note","content":[{"type":"paragraph","inlineContent":[{"type":"text","text":"Even though the closure refers to "},{"code":"self","type":"codeVoice"},{"text":" multiple times,","type":"text"},{"text":" ","type":"text"},{"text":"it only captures one strong reference to the ","type":"text"},{"code":"HTMLElement","type":"codeVoice"},{"text":" instance.","type":"text"}]}],"type":"aside","style":"note"},{"inlineContent":[{"type":"text","text":"If you set the "},{"code":"paragraph","type":"codeVoice"},{"type":"text","text":" variable to "},{"type":"codeVoice","code":"nil"},{"text":" ","type":"text"},{"type":"text","text":"and break its strong reference to the "},{"type":"codeVoice","code":"HTMLElement"},{"text":" instance,","type":"text"},{"type":"text","text":" "},{"type":"text","text":"the strong reference cycle prevents deallocating"},{"type":"text","text":" "},{"text":"both the ","type":"text"},{"type":"codeVoice","code":"HTMLElement"},{"text":" instance and its closure:","type":"text"}],"type":"paragraph"},{"type":"codeListing","syntax":"swift","code":["paragraph = nil"]},{"type":"paragraph","inlineContent":[{"type":"text","text":"Note that the message in the "},{"code":"HTMLElement","type":"codeVoice"},{"text":" deinitializer isn’t printed,","type":"text"},{"type":"text","text":" "},{"type":"text","text":"which shows that the "},{"type":"codeVoice","code":"HTMLElement"},{"text":" instance isn’t deallocated.","type":"text"}]},{"level":2,"anchor":"Resolving-Strong-Reference-Cycles-for-Closures","type":"heading","text":"Resolving Strong Reference Cycles for Closures"},{"type":"paragraph","inlineContent":[{"text":"You resolve a strong reference cycle between a closure and a class instance","type":"text"},{"type":"text","text":" "},{"type":"text","text":"by defining a "},{"inlineContent":[{"type":"text","text":"capture list"}],"type":"emphasis"},{"type":"text","text":" as part of the closure’s definition."},{"text":" ","type":"text"},{"text":"A capture list defines the rules to use when capturing one or more reference types","type":"text"},{"type":"text","text":" "},{"text":"within the closure’s body.","type":"text"},{"type":"text","text":" "},{"text":"As with strong reference cycles between two class instances,","type":"text"},{"text":" ","type":"text"},{"type":"text","text":"you declare each captured reference to be a weak or unowned reference"},{"text":" ","type":"text"},{"type":"text","text":"rather than a strong reference."},{"type":"text","text":" "},{"type":"text","text":"The appropriate choice of weak or unowned depends on"},{"text":" ","type":"text"},{"type":"text","text":"the relationships between the different parts of your code."}]},{"type":"aside","name":"Note","style":"note","content":[{"inlineContent":[{"type":"text","text":"Swift requires you to write "},{"type":"codeVoice","code":"self.someProperty"},{"text":" or ","type":"text"},{"type":"codeVoice","code":"self.someMethod()"},{"text":" ","type":"text"},{"text":"(rather than just ","type":"text"},{"type":"codeVoice","code":"someProperty"},{"text":" or ","type":"text"},{"type":"codeVoice","code":"someMethod()"},{"text":")","type":"text"},{"text":" ","type":"text"},{"type":"text","text":"whenever you refer to a member of "},{"type":"codeVoice","code":"self"},{"text":" within a closure.","type":"text"},{"type":"text","text":" "},{"type":"text","text":"This helps you remember that it’s possible to capture "},{"type":"codeVoice","code":"self"},{"type":"text","text":" by accident."}],"type":"paragraph"}]},{"anchor":"Defining-a-Capture-List","text":"Defining a Capture List","type":"heading","level":3},{"inlineContent":[{"type":"text","text":"Each item in a capture list is a pairing of the "},{"code":"weak","type":"codeVoice"},{"text":" or ","type":"text"},{"type":"codeVoice","code":"unowned"},{"text":" keyword","type":"text"},{"text":" ","type":"text"},{"type":"text","text":"with a reference to a class instance (such as "},{"type":"codeVoice","code":"self"},{"text":")","type":"text"},{"text":" ","type":"text"},{"type":"text","text":"or a variable initialized with some value (such as "},{"type":"codeVoice","code":"delegate = self.delegate"},{"text":").","type":"text"},{"text":" ","type":"text"},{"type":"text","text":"These pairings are written within a pair of square braces, separated by commas."}],"type":"paragraph"},{"inlineContent":[{"text":"Place the capture list before a closure’s parameter list and return type","type":"text"},{"type":"text","text":" "},{"text":"if they’re provided:","type":"text"}],"type":"paragraph"},{"syntax":"swift","code":["lazy var someClosure = {","        [unowned self, weak delegate = self.delegate]","        (index: Int, stringToProcess: String) -> String in","    \/\/ closure body goes here","}"],"type":"codeListing"},{"type":"paragraph","inlineContent":[{"type":"text","text":"If a closure doesn’t specify a parameter list or return type"},{"text":" ","type":"text"},{"type":"text","text":"because they can be inferred from context,"},{"type":"text","text":" "},{"type":"text","text":"place the capture list at the very start of the closure,"},{"type":"text","text":" "},{"type":"text","text":"followed by the "},{"code":"in","type":"codeVoice"},{"type":"text","text":" keyword:"}]},{"type":"codeListing","syntax":"swift","code":["lazy var someClosure = {","        [unowned self, weak delegate = self.delegate] in","    \/\/ closure body goes here","}"]},{"text":"Weak and Unowned References","type":"heading","anchor":"Weak-and-Unowned-References","level":3},{"type":"paragraph","inlineContent":[{"text":"Define a capture in a closure as an unowned reference","type":"text"},{"type":"text","text":" "},{"type":"text","text":"when the closure and the instance it captures will always refer to each other,"},{"text":" ","type":"text"},{"text":"and will always be deallocated at the same time.","type":"text"}]},{"type":"paragraph","inlineContent":[{"text":"Conversely, define a capture as a weak reference when the captured reference","type":"text"},{"text":" ","type":"text"},{"type":"text","text":"may become "},{"type":"codeVoice","code":"nil"},{"text":" at some point in the future.","type":"text"},{"text":" ","type":"text"},{"type":"text","text":"Weak references are always of an optional type,"},{"text":" ","type":"text"},{"type":"text","text":"and automatically become "},{"type":"codeVoice","code":"nil"},{"text":" when the instance they reference is deallocated.","type":"text"},{"text":" ","type":"text"},{"text":"This enables you to check for their existence within the closure’s body.","type":"text"}]},{"type":"aside","content":[{"inlineContent":[{"type":"text","text":"If the captured reference will never become "},{"type":"codeVoice","code":"nil"},{"type":"text","text":","},{"type":"text","text":" "},{"type":"text","text":"it should always be captured as an unowned reference,"},{"type":"text","text":" "},{"type":"text","text":"rather than a weak reference."}],"type":"paragraph"}],"style":"note","name":"Note"},{"type":"paragraph","inlineContent":[{"type":"text","text":"An unowned reference is the appropriate capture method to use to resolve"},{"type":"text","text":" "},{"type":"text","text":"the strong reference cycle in the "},{"type":"codeVoice","code":"HTMLElement"},{"type":"text","text":" example"},{"type":"text","text":" "},{"text":"from ","type":"text"},{"type":"reference","isActive":true,"identifier":"doc:\/\/org.swift.tspl\/documentation\/The-Swift-Programming-Language\/AutomaticReferenceCounting#Strong-Reference-Cycles-for-Closures"},{"type":"text","text":" above."},{"type":"text","text":" "},{"text":"Here’s how you write the ","type":"text"},{"type":"codeVoice","code":"HTMLElement"},{"type":"text","text":" class to avoid the cycle:"}]},{"type":"codeListing","code":["class HTMLElement {","","    let name: String","    let text: String?","","    lazy var asHTML: () -> String = {","            [unowned self] in","        if let text = self.text {","            return \"<\\(self.name)>\\(text)<\/\\(self.name)>\"","        } else {","            return \"<\\(self.name) \/>\"","        }","    }","","    init(name: String, text: String? = nil) {","        self.name = name","        self.text = text","    }","","    deinit {","        print(\"\\(name) is being deinitialized\")","    }","","}"],"syntax":"swift"},{"type":"paragraph","inlineContent":[{"text":"This implementation of ","type":"text"},{"type":"codeVoice","code":"HTMLElement"},{"text":" is identical to the previous implementation,","type":"text"},{"text":" ","type":"text"},{"text":"apart from the addition of a capture list within the ","type":"text"},{"type":"codeVoice","code":"asHTML"},{"type":"text","text":" closure."},{"text":" ","type":"text"},{"type":"text","text":"In this case, the capture list is "},{"type":"codeVoice","code":"[unowned self]"},{"text":",","type":"text"},{"text":" ","type":"text"},{"type":"text","text":"which means “capture self as an unowned reference rather than a strong reference”."}]},{"inlineContent":[{"text":"You can create and print an ","type":"text"},{"type":"codeVoice","code":"HTMLElement"},{"type":"text","text":" instance as before:"}],"type":"paragraph"},{"type":"codeListing","code":["var paragraph: HTMLElement? = HTMLElement(name: \"p\", text: \"hello, world\")","print(paragraph!.asHTML())","\/\/ Prints \"<p>hello, world<\/p>\""],"syntax":"swift"},{"inlineContent":[{"text":"Here’s how the references look with the capture list in place:","type":"text"}],"type":"paragraph"},{"type":"paragraph","inlineContent":[{"type":"image","identifier":"closureReferenceCycle02"}]},{"type":"paragraph","inlineContent":[{"type":"text","text":"This time, the capture of "},{"code":"self","type":"codeVoice"},{"type":"text","text":" by the closure is an unowned reference,"},{"type":"text","text":" "},{"text":"and doesn’t keep a strong hold on the ","type":"text"},{"type":"codeVoice","code":"HTMLElement"},{"text":" instance it has captured.","type":"text"},{"text":" ","type":"text"},{"type":"text","text":"If you set the strong reference from the "},{"type":"codeVoice","code":"paragraph"},{"text":" variable to ","type":"text"},{"code":"nil","type":"codeVoice"},{"text":",","type":"text"},{"type":"text","text":" "},{"type":"text","text":"the "},{"type":"codeVoice","code":"HTMLElement"},{"type":"text","text":" instance is deallocated,"},{"text":" ","type":"text"},{"type":"text","text":"as can be seen from the printing of its deinitializer message in the example below:"}]},{"type":"codeListing","syntax":"swift","code":["paragraph = nil","\/\/ Prints \"p is being deinitialized\""]},{"type":"paragraph","inlineContent":[{"text":"For more information about capture lists,","type":"text"},{"text":" ","type":"text"},{"text":"see ","type":"text"},{"type":"reference","identifier":"doc:\/\/org.swift.tspl\/documentation\/The-Swift-Programming-Language\/Expressions#Capture-Lists","isActive":true},{"type":"text","text":"."}]},{"type":"aside","name":"Beta Software","style":"note","content":[{"type":"paragraph","inlineContent":[{"type":"text","text":""}]},{"type":"paragraph","inlineContent":[{"text":"This documentation contains preliminary information about an API or technology in development. This information is subject to change, and software implemented according to this documentation should be tested with final operating system software.","type":"text"}]},{"inlineContent":[{"type":"text","text":"Learn more about using "},{"type":"reference","identifier":"https:\/\/developer.apple.com\/support\/beta-software\/","isActive":true},{"type":"text","text":"."}],"type":"paragraph"}]}]}],"schemaVersion":{"major":0,"minor":3,"patch":0},"kind":"article","sections":[],"hierarchy":{"paths":[["doc:\/\/org.swift.tspl\/documentation\/The-Swift-Programming-Language"]]},"references":{"https://developer.apple.com/support/beta-software/":{"url":"https:\/\/developer.apple.com\/support\/beta-software\/","identifier":"https:\/\/developer.apple.com\/support\/beta-software\/","title":"Apple’s beta software","type":"link","titleInlineContent":[{"type":"text","text":"Apple’s beta software"}]},"referenceCycle01":{"type":"image","alt":null,"variants":[{"url":"\/images\/org.swift.tspl\/referenceCycle01@2x.png","traits":["2x","light"]},{"traits":["2x","dark"],"url":"\/images\/org.swift.tspl\/referenceCycle01~dark@2x.png"}],"identifier":"referenceCycle01"},"doc://org.swift.tspl/documentation/The-Swift-Programming-Language/TheBasics#Implicitly-Unwrapped-Optionals":{"url":"\/documentation\/the-swift-programming-language\/thebasics#Implicitly-Unwrapped-Optionals","type":"topic","abstract":[],"kind":"section","identifier":"doc:\/\/org.swift.tspl\/documentation\/The-Swift-Programming-Language\/TheBasics#Implicitly-Unwrapped-Optionals","title":"Implicitly Unwrapped Optionals"},"doc://org.swift.tspl/documentation/The-Swift-Programming-Language/AutomaticReferenceCounting#Strong-Reference-Cycles-for-Closures":{"url":"\/documentation\/the-swift-programming-language\/automaticreferencecounting#Strong-Reference-Cycles-for-Closures","type":"topic","abstract":[],"kind":"section","identifier":"doc:\/\/org.swift.tspl\/documentation\/The-Swift-Programming-Language\/AutomaticReferenceCounting#Strong-Reference-Cycles-for-Closures","title":"Strong Reference Cycles for Closures"},"doc://org.swift.tspl/documentation/The-Swift-Programming-Language/Initialization#Two-Phase-Initialization":{"url":"\/documentation\/the-swift-programming-language\/initialization#Two-Phase-Initialization","type":"topic","abstract":[],"kind":"section","identifier":"doc:\/\/org.swift.tspl\/documentation\/The-Swift-Programming-Language\/Initialization#Two-Phase-Initialization","title":"Two-Phase Initialization"},"doc://org.swift.tspl/documentation/The-Swift-Programming-Language/Expressions#Capture-Lists":{"url":"\/documentation\/the-swift-programming-language\/expressions#Capture-Lists","type":"topic","abstract":[],"kind":"section","identifier":"doc:\/\/org.swift.tspl\/documentation\/The-Swift-Programming-Language\/Expressions#Capture-Lists","title":"Capture Lists"},"doc://org.swift.tspl/documentation/The-Swift-Programming-Language":{"title":"The Swift Programming Language (6.0 beta)","abstract":[],"type":"topic","identifier":"doc:\/\/org.swift.tspl\/documentation\/The-Swift-Programming-Language","url":"\/documentation\/the-swift-programming-language","role":"collection","kind":"article"},"closureReferenceCycle01":{"type":"image","alt":null,"variants":[{"url":"\/images\/org.swift.tspl\/closureReferenceCycle01@2x.png","traits":["2x","light"]},{"traits":["2x","dark"],"url":"\/images\/org.swift.tspl\/closureReferenceCycle01~dark@2x.png"}],"identifier":"closureReferenceCycle01"},"unownedReference01":{"alt":null,"variants":[{"url":"\/images\/org.swift.tspl\/unownedReference01@2x.png","traits":["2x","light"]},{"traits":["2x","dark"],"url":"\/images\/org.swift.tspl\/unownedReference01~dark@2x.png"}],"identifier":"unownedReference01","type":"image"},"unownedReference02":{"alt":null,"variants":[{"url":"\/images\/org.swift.tspl\/unownedReference02@2x.png","traits":["2x","light"]},{"traits":["2x","dark"],"url":"\/images\/org.swift.tspl\/unownedReference02~dark@2x.png"}],"identifier":"unownedReference02","type":"image"},"weakReference01":{"alt":null,"variants":[{"url":"\/images\/org.swift.tspl\/weakReference01@2x.png","traits":["2x","light"]},{"traits":["2x","dark"],"url":"\/images\/org.swift.tspl\/weakReference01~dark@2x.png"}],"identifier":"weakReference01","type":"image"},"referenceCycle02":{"alt":null,"variants":[{"url":"\/images\/org.swift.tspl\/referenceCycle02@2x.png","traits":["2x","light"]},{"traits":["2x","dark"],"url":"\/images\/org.swift.tspl\/referenceCycle02~dark@2x.png"}],"identifier":"referenceCycle02","type":"image"},"https://developer.apple.com/library/content/releasenotes/ObjectiveC/RN-TransitioningToARC/Introduction/Introduction.html":{"url":"https:\/\/developer.apple.com\/library\/content\/releasenotes\/ObjectiveC\/RN-TransitioningToARC\/Introduction\/Introduction.html","identifier":"https:\/\/developer.apple.com\/library\/content\/releasenotes\/ObjectiveC\/RN-TransitioningToARC\/Introduction\/Introduction.html","title":"Transitioning to ARC Release Notes","type":"link","titleInlineContent":[{"type":"text","text":"Transitioning to ARC Release Notes"}]},"weakReference02":{"alt":null,"variants":[{"url":"\/images\/org.swift.tspl\/weakReference02@2x.png","traits":["2x","light"]},{"traits":["2x","dark"],"url":"\/images\/org.swift.tspl\/weakReference02~dark@2x.png"}],"identifier":"weakReference02","type":"image"},"doc://org.swift.tspl/documentation/The-Swift-Programming-Language/AutomaticReferenceCounting#Resolving-Strong-Reference-Cycles-Between-Class-Instances":{"url":"\/documentation\/the-swift-programming-language\/automaticreferencecounting#Resolving-Strong-Reference-Cycles-Between-Class-Instances","abstract":[],"kind":"section","identifier":"doc:\/\/org.swift.tspl\/documentation\/The-Swift-Programming-Language\/AutomaticReferenceCounting#Resolving-Strong-Reference-Cycles-Between-Class-Instances","title":"Resolving Strong Reference Cycles Between Class Instances","type":"topic"},"referenceCycle03":{"variants":[{"url":"\/images\/org.swift.tspl\/referenceCycle03@2x.png","traits":["2x","light"]},{"traits":["2x","dark"],"url":"\/images\/org.swift.tspl\/referenceCycle03~dark@2x.png"}],"alt":null,"identifier":"referenceCycle03","type":"image"},"closureReferenceCycle02":{"alt":null,"variants":[{"url":"\/images\/org.swift.tspl\/closureReferenceCycle02@2x.png","traits":["2x","light"]},{"traits":["2x","dark"],"url":"\/images\/org.swift.tspl\/closureReferenceCycle02~dark@2x.png"}],"identifier":"closureReferenceCycle02","type":"image"},"unownedOptionalReference":{"variants":[{"url":"\/images\/org.swift.tspl\/unownedOptionalReference@2x.png","traits":["2x","light"]},{"traits":["2x","dark"],"url":"\/images\/org.swift.tspl\/unownedOptionalReference~dark@2x.png"}],"alt":null,"identifier":"unownedOptionalReference","type":"image"},"doc://org.swift.tspl/documentation/The-Swift-Programming-Language/Closures#Capturing-Values":{"url":"\/documentation\/the-swift-programming-language\/closures#Capturing-Values","abstract":[],"kind":"section","identifier":"doc:\/\/org.swift.tspl\/documentation\/The-Swift-Programming-Language\/Closures#Capturing-Values","title":"Capturing Values","type":"topic"},"weakReference03":{"alt":null,"variants":[{"url":"\/images\/org.swift.tspl\/weakReference03@2x.png","traits":["2x","light"]},{"traits":["2x","dark"],"url":"\/images\/org.swift.tspl\/weakReference03~dark@2x.png"}],"identifier":"weakReference03","type":"image"}}}